ipyelk/__init__.py
ipyelk/constants.py
ipyelk/exceptions.py
ipyelk/js.py
ipyelk/py.typed
ipyelk/styled_widget.py
ipyelk/trait_types.py
ipyelk/util.py
ipyelk/contrib/__init__.py
ipyelk/contrib/library/__init__.py
ipyelk/contrib/library/activity.py
ipyelk/contrib/library/block.py
ipyelk/contrib/library/logic_gates.py
ipyelk/contrib/molds/__init__.py
ipyelk/contrib/molds/connectors.py
ipyelk/contrib/molds/structures.py
ipyelk/diagram/__init__.py
ipyelk/diagram/diagram.py
ipyelk/diagram/export.py
ipyelk/diagram/flow.py
ipyelk/diagram/sprotty_viewer.py
ipyelk/diagram/viewer.py
ipyelk/elements/__init__.py
ipyelk/elements/common.py
ipyelk/elements/elements.py
ipyelk/elements/extended.py
ipyelk/elements/index.py
ipyelk/elements/mark_factory.py
ipyelk/elements/registry.py
ipyelk/elements/serialization.py
ipyelk/elements/shapes.py
ipyelk/elements/symbol.py
ipyelk/elements/layout_options/__init__.py
ipyelk/elements/layout_options/edge_options.py
ipyelk/elements/layout_options/layout.py
ipyelk/elements/layout_options/model.py
ipyelk/elements/layout_options/node_options.py
ipyelk/elements/layout_options/port_options.py
ipyelk/elements/layout_options/selection_widgets.py
ipyelk/elements/layout_options/spacing_options.py
ipyelk/elements/layout_options/wrapping_options.py
ipyelk/loaders/__init__.py
ipyelk/loaders/element_loader.py
ipyelk/loaders/json.py
ipyelk/loaders/loader.py
ipyelk/loaders/nx/__init__.py
ipyelk/loaders/nx/nxloader.py
ipyelk/loaders/nx/nxutils.py
ipyelk/pipes/__init__.py
ipyelk/pipes/base.py
ipyelk/pipes/elkjs.py
ipyelk/pipes/flows.py
ipyelk/pipes/mappings.py
ipyelk/pipes/marks.py
ipyelk/pipes/pipeline.py
ipyelk/pipes/text_sizer.py
ipyelk/pipes/util.py
ipyelk/pipes/valid.py
ipyelk/pipes/visibility.py
ipyelk/schema/README.md
ipyelk/schema/__init__.py
ipyelk/schema/elkschema.json
ipyelk/schema/validator.py
ipyelk/tools/__init__.py
ipyelk/tools/collapser.py
ipyelk/tools/contol_overlay.py
ipyelk/tools/painter.py
ipyelk/tools/progress.py
ipyelk/tools/tool.py
ipyelk-2.1.1.dist-info/LICENSE.txt
ipyelk-2.1.1.dist-info/WHEEL
ipyelk-2.1.1.dist-info/METADATA
ipyelk-2.1.1.dist-info/RECORD
