Metadata-Version: 2.1
Name: ipyelk
Version: 2.1.1
Summary: ELK widget for Jupyter
Author-email: Dane Freeman <dane.freeman@gtri.gatech.edu>
Requires-Python: >=3.9
Classifier: Framework :: Jupyter :: JupyterLab :: 4
Classifier: Framework :: Jupyter :: JupyterLab :: Extensions :: Prebuilt
Classifier: Framework :: Jupyter :: JupyterLab :: Extensions
Classifier: Framework :: Jupyter :: JupyterLab
Classifier: Framework :: Jupyter
Classifier: Intended Audience :: Developers
Classifier: Intended Audience :: Science/Research
Classifier: License :: OSI Approved :: BSD License
Classifier: Programming Language :: Python :: 3 :: Only
Classifier: Programming Language :: Python :: 3.10
Classifier: Programming Language :: Python :: 3.11
Classifier: Programming Language :: Python :: 3.12
Classifier: Programming Language :: Python :: 3.13
Classifier: Programming Language :: Python :: 3.9
Classifier: Programming Language :: Python :: 3
Requires-Dist: ipywidgets >=8.0.1,<9
Requires-Dist: jsonschema >=4.18
Requires-Dist: networkx
Requires-Dist: pydantic >=1.10.17,<3
Project-URL: Bug Tracker, https://github.com/jupyrdf/ipyelk/issues
Project-URL: Changelog, https://github.com/jupyrdf/ipyelk/blob/main/CHANGELOG.md
Project-URL: Documentation, https://ipyelk.rtfd.io
Project-URL: Source, https://github.com/jupyrdf/ipyelk
